ultimate_rvc/__init__.py
ultimate_rvc/cli/__init__.py
ultimate_rvc/cli/common.py
ultimate_rvc/cli/generate/__init__.py
ultimate_rvc/cli/generate/main.py
ultimate_rvc/cli/generate/song_cover.py
ultimate_rvc/cli/generate/speech.py
ultimate_rvc/cli/main.py
ultimate_rvc/cli/train/__init__.py
ultimate_rvc/cli/train/main.py
ultimate_rvc/cli/typing_extra.py
ultimate_rvc/common.py
ultimate_rvc/core/__init__.py
ultimate_rvc/core/common.py
ultimate_rvc/core/exceptions.py
ultimate_rvc/core/generate/__init__.py
ultimate_rvc/core/generate/common.py
ultimate_rvc/core/generate/song_cover.py
ultimate_rvc/core/generate/speech.py
ultimate_rvc/core/generate/typing_extra.py
ultimate_rvc/core/main.py
ultimate_rvc/core/manage/__init__.py
ultimate_rvc/core/manage/audio.py
ultimate_rvc/core/manage/common.py
ultimate_rvc/core/manage/config.py
ultimate_rvc/core/manage/custom_pretrains.json
ultimate_rvc/core/manage/models.py
ultimate_rvc/core/manage/public_models.json
ultimate_rvc/core/manage/settings.py
ultimate_rvc/core/manage/typing_extra.py
ultimate_rvc/core/train/__init__.py
ultimate_rvc/core/train/common.py
ultimate_rvc/core/train/extract.py
ultimate_rvc/core/train/prepare.py
ultimate_rvc/core/train/train.py
ultimate_rvc/core/train/typing_extra.py
ultimate_rvc/py.typed
ultimate_rvc/rvc/__init__.py
ultimate_rvc/rvc/common.py
ultimate_rvc/rvc/configs/32000.json
ultimate_rvc/rvc/configs/40000.json
ultimate_rvc/rvc/configs/48000.json
ultimate_rvc/rvc/configs/config.py
ultimate_rvc/rvc/infer/infer.py
ultimate_rvc/rvc/infer/pipeline.py
ultimate_rvc/rvc/infer/typing_extra.py
ultimate_rvc/rvc/lib/algorithm/__init__.py
ultimate_rvc/rvc/lib/algorithm/attentions.py
ultimate_rvc/rvc/lib/algorithm/commons.py
ultimate_rvc/rvc/lib/algorithm/discriminators.py
ultimate_rvc/rvc/lib/algorithm/encoders.py
ultimate_rvc/rvc/lib/algorithm/generators/__init__.py
ultimate_rvc/rvc/lib/algorithm/generators/hifigan.py
ultimate_rvc/rvc/lib/algorithm/generators/hifigan_mrf.py
ultimate_rvc-0.6.0.dist-info/WHEEL
ultimate_rvc-0.6.0.dist-info/entry_points.txt
ultimate_rvc-0.6.0.dist-info/METADATA
ultimate_rvc-0.6.0.dist-info/RECORD
