Metadata-Version: 2.3
Name: ultimate-rvc
Version: 0.6.0
Summary: Ultimate RVC
Requires-Dist: pydantic==2.11.7
Requires-Dist: lazy-loader==0.4.0
Requires-Dist: typer==0.20.0
Requires-Dist: requests==2.32.5
Requires-Dist: yt-dlp[default]>=2025.11.12
Requires-Dist: nodejs-wheel-binaries==24.12.0
Requires-Dist: wget==3.2
Requires-Dist: numpy==2.3.5
Requires-Dist: scipy==1.16.3
Requires-Dist: matplotlib==3.10.8
Requires-Dist: tqdm==4.67.1
Requires-Dist: gradio==5.49.1
Requires-Dist: pandas-stubs==2.3.3.251201
Requires-Dist: torchcrepe==0.0.24
Requires-Dist: faiss-cpu==1.13.1
Requires-Dist: onnxruntime-gpu==1.23.2
Requires-Dist: local-attention==1.11.2
Requires-Dist: einops==0.8.1
Requires-Dist: transformers==4.57.3
Requires-Dist: torchfcpe==0.0.4
Requires-Dist: tensorboardx==2.6.4
Requires-Dist: tensorboard==2.20.0
Requires-Dist: torch-tb-profiler==0.4.3
Requires-Dist: static-ffmpeg==2.13
Requires-Dist: static-sox==1.0.2
Requires-Dist: typed-ffmpeg==3.8.1
Requires-Dist: soundfile==0.13.1
Requires-Dist: librosa==0.11.0
Requires-Dist: sox==1.5.0
Requires-Dist: soxr==1.0.0
Requires-Dist: pydub==0.25.1
Requires-Dist: pydub-stubs==0.25.1.6
Requires-Dist: pedalboard==0.9.19
Requires-Dist: audio-separator[gpu]==0.40.0
Requires-Dist: noisereduce==3.0.3
Requires-Dist: edge-tts==7.2.7
Requires-Dist: torch==2.7.1+cu128 ; extra == 'cuda'
Requires-Dist: torchaudio==2.7.1+cu128 ; extra == 'cuda'
Requires-Dist: torch==2.6.0+rocm6.2.4 ; sys_platform == 'linux' and extra == 'rocm'
Requires-Dist: torchaudio==2.6.0+rocm6.2.4 ; sys_platform == 'linux' and extra == 'rocm'
Requires-Dist: pytorch-triton-rocm==3.2.0 ; sys_platform == 'linux' and extra == 'rocm'
Requires-Python: >=3.12, <3.14
Provides-Extra: cuda
Provides-Extra: rocm
